bizztreat_base/__init__.py
bizztreat_base/config.py
bizztreat_base/utils/__init__.py
bizztreat_base/utils/writer.py
bizztreat_base-0.3.0.dist-info/WHEEL
bizztreat_base-0.3.0.dist-info/METADATA
bizztreat_base-0.3.0.dist-info/RECORD
