Metadata-Version: 2.1
Name: bizztreat-base
Version: 0.3.0
Summary: Set of helpers to help you build Bizzflow components easily
Author: Tomas Votava
Author-email: tomas.votava@bizztreat.com
Requires-Python: >=3.9,<4.0
Classifier: Programming Language :: Python :: 3
Classifier: Programming Language :: Python :: 3.9
Classifier: Programming Language :: Python :: 3.10
Requires-Dist: jsonschema (>=3.2.0,<4.0.0)
